dijkstra_algorithm/config.py
dijkstra_algorithm/dijkstra_strategy.py
dijkstra_algorithm/functions/make_matrix.py
dijkstra_algorithm/main.py
dijkstra_algorithm/work_with_data/create_chart.py
dijkstra_algorithm/work_with_data/generate_data.py
dijkstra_algorithm/work_with_data/load_testing_mesurenets/load_testing_naiv_measurements/1621689952.872828.csv
dijkstra_algorithm/work_with_data/load_testing_mesurenets/load_testing_naiv_measurements/naiv_graph.png
dijkstra_algorithm/work_with_data/load_testing_mesurenets/load_testing_set_measurements/1621691961.3470256.csv
dijkstra_algorithm/work_with_data/load_testing_mesurenets/load_testing_set_measurements/set_graph.png
dijkstra_algorithm/work_with_data/measure_time.py
dijkstra_algorithm-0.1.0.dist-info/entry_points.txt
dijkstra_algorithm-0.1.0.dist-info/WHEEL
dijkstra_algorithm-0.1.0.dist-info/METADATA
dijkstra_algorithm-0.1.0.dist-info/RECORD
