Metadata-Version: 2.1
Name: dijkstra-algorithm
Version: 0.1.0
Summary: 
Author: Ilnar Gomelyanov
Author-email: hibushland@gmail.com
Requires-Python: >=3.8,<4.0
Classifier: Programming Language :: Python :: 3
Classifier: Programming Language :: Python :: 3.8
Classifier: Programming Language :: Python :: 3.9
Requires-Dist: click (>=8.0.0,<9.0.0)
Requires-Dist: matplotlib (>=3.4.2,<4.0.0)
Requires-Dist: pandas (>=1.2.4,<2.0.0)
Requires-Dist: python-dotenv (>=0.17.1,<0.18.0)
